{
  "slug": "wordsworth-tlumaczenie-20-lutego",
  "title": {
    "pl": "Tłumaczenie Ody Wordswortha - nietypowa współpraca",
    "en": "Tłumaczenie Ody Wordswortha - nietypowa współpraca"
  },
  "excerpt": {
    "pl": "Jedyne takie tłumaczenie Ody Wordswortha... nie uwierzycie owocem jakiej szczególnie nietypowej współpracy ono jest...",
    "en": "Jedyne takie tłumaczenie Ody Wordswortha... nie uwierzycie owocem jakiej szczególnie nietypowej współpracy ono jest..."
  },
  "content": {
    "pl": "Jedyne takie tłumaczenie Ody Wordswortha...\n\nnie uwierzycie owocem jakiej szczególnie nietypowej współpracy ono jest... nie jest idealne bo i ten kawałek poezji jest bardzo trudny ale... cóż, jest to przygoda...\n\nOda o przeczuciach nieśmiertelności... tytuł chyba jeszcze za Stanisławem Barańczakiem ale lepszy byłby chyba \"Przebłyski Pamięci Nieśmiertelności ze wspomnień wczesnego dzieciństwa\"",
    "en": "Jedyne takie tłumaczenie Ody Wordswortha...\n\nnie uwierzycie owocem jakiej szczególnie nietypowej współpracy ono jest... nie jest idealne bo i ten kawałek poezji jest bardzo trudny ale... cóż, jest to przygoda...\n\nOda o przeczuciach nieśmiertelności... tytuł chyba jeszcze za Stanisławem Barańczakiem ale lepszy byłby chyba \"Przebłyski Pamięci Nieśmiertelności ze wspomnień wczesnego dzieciństwa\""
  },
  "date": "2025-02-20",
  "category": "writing",
  "tags": ["translation", "poetry"],
  "author": "Sebastian Proba",
  "featured": false
}
